stream_django/__init__.py
stream_django/activity.py
stream_django/apps.py
stream_django/client.py
stream_django/conf.py
stream_django/context_processors.py
stream_django/enrich.py
stream_django/exceptions.py
stream_django/feed_manager.py
stream_django/managers.py
stream_django/models.py
stream_django/utils.py
stream_django/templatetags/__init__.py
stream_django/templatetags/activity_tags.py
stream_django-1.8.0.dist-info/LICENSE
stream_django-1.8.0.dist-info/METADATA
stream_django-1.8.0.dist-info/WHEEL
stream_django-1.8.0.dist-info/top_level.txt
stream_django-1.8.0.dist-info/RECORD
