Metadata-Version: 2.1
Name: stream-django
Version: 1.8.0
Summary: A Django app to build activity, news and notification feeds.
Home-page: https://github.com/GetStream/stream-django
Author: Tommaso Barbugli
Author-email: tbarbugli@gmail.com
License: BSD License
Project-URL: Bug Tracker, https://github.com/GetStream/stream-django/issues
Project-URL: Documentation, https://getstream.io/activity-feeds/docs/python/adding_activities/?language=python
Project-URL: Release Notes, https://github.com/GetStream/stream-django/releases/tag/1.8.0
Platform: UNKNOWN
Classifier: Environment :: Web Environment
Classifier: Framework :: Django
Classifier: Intended Audience :: Developers
Classifier: License :: OSI Approved :: BSD License
Classifier: Operating System :: OS Independent
Classifier: Programming Language :: Python
Classifier: Programming Language :: Python :: 2.7
Classifier: Programming Language :: Python :: 3
Classifier: Programming Language :: Python :: 3.6
Classifier: Programming Language :: Python :: 3.7
Classifier: Programming Language :: Python :: 3.8
Classifier: Programming Language :: Python :: 3.9
Classifier: Programming Language :: Python :: 3.10
Classifier: Topic :: Internet :: WWW/HTTP
Classifier: Topic :: Internet :: WWW/HTTP :: Dynamic Content
Provides-Extra: test
Provides-Extra: ci
License-File: LICENSE
